np_stream/__init__.py
np_stream/benchmark.py
np_stream/npy.py
np_stream/npy_utils.py
np_stream/npz.py
np_stream/test.py
np_stream/utils.py
np_stream/zip.py
np_stream-0.1.0.dist-info/METADATA
np_stream-0.1.0.dist-info/WHEEL
np_stream-0.1.0.dist-info/top_level.txt
np_stream-0.1.0.dist-info/RECORD
