Metadata-Version: 2.1
Name: np-stream
Version: 0.1.0
Summary: A replacement for the np.load(), np.save() and np.savez_compressed() NumPy functions with support for streaming data on one dimension
License: EUPL-1.2
Project-URL: repository, https://github.com/slietar/np-stream
Requires-Python: >=3.11
Requires-Dist: numpy (~=1.23)
